[{"id":"4551","name":"Red River Theatres","address":"11 S. Main St.","city":"Concord","state":"NH","zip":"03301","distance":"16.59882164001465","lon":"-71.535210","lat":"43.203812","theaterChainName":"Independent Chains","ticketType":"STANDARD"},{"id":"456","name":"Regal Concord 10","address":"282 Loudon Road","city":"Concord","state":"NH","zip":"03301","distance":"18.397693634033203","lon":"-71.485909","lat":"43.225010","theaterChainName":"Regal Cinemas","ticketType":"STANDARD"},{"id":"4604","name":"Smitty's Cinema","address":"630 W. Main St.","city":"Tilton","state":"NH","zip":"03276","distance":"14.676383018493652","lon":"-71.619507","lat":"43.446720","theaterChainName":"Independent Chains","ticketType":"STANDARD"},{"id":"832","name":"Gilford Cinema 8","address":"9 Old Lake Shore Road","city":"Gilford","state":"NH","zip":"03249","distance":"24.73121452331543","lon":"-72.320198","lat":"43.364388","theaterChainName":"Boston Culinary Group","ticketType":"STANDARD"},{"id":"1795","name":"Claremont Cinema 6","address":"345 Washington Street","city":"Claremont","state":"NH","zip":"03743","distance":"24.73121452331543","lon":"-72.320198","lat":"43.364388","theaterChainName":"Boston Culinary Group","ticketType":"STANDARD"}]