[{"id":"1346","name":"Bow Tie Cinemas Plaza 3","address":"2 Railroad Ave.","city":"Greenwich","state":"CT","zip":"06830","distance":"23.193252563476562","lon":"-73.624985","lat":"41.021488","theaterChainName":"Bow-Tie Cinemas","ticketType":"STANDARD"},{"id":"3067","name":"Carmel Movieplex 8","address":"150 Route 52","city":"Carmel","state":"NY","zip":"10512","distance":"23.124284744262695","lon":"-73.679596","lat":"41.434280","theaterChainName":"Independent Chains","ticketType":"STANDARD"},{"id":"1530","name":"Bow Tie Cinemas Mt Kisco Cinemas ","address":"144 Main St.","city":"Mount Kisco","state":"NY","zip":"10549","distance":"14.19761848449707","lon":"-73.727432","lat":"41.204987","theaterChainName":"Bow-Tie Cinemas","ticketType":"STANDARD"},{"id":"3888","name":"AMC Loews Port Chester 14","address":"40 Westchester Ave.","city":"Port Chester","state":"NY","zip":"10573","distance":"22.48128890991211","lon":"-73.662392","lat":"40.999760","theaterChainName":"AMC Theatres","ticketType":"STANDARD"},{"id":"3369","name":"Jacob Burns Film Center","address":"364 Manville Road","city":"Pleasantville","state":"NY","zip":"10570","distance":"11.812458992004395","lon":"-73.791603","lat":"41.135048","theaterChainName":"Independent Chains","ticketType":"STANDARD"},{"id":"873","name":"UA Cortlandt Town Center Stadium 11","address":"3131 E. Main St.","city":"Mohegan Lake","state":"NY","zip":"10547","distance":"10.1400146484375","lon":"-73.868340","lat":"41.310097","theaterChainName":"United Artists","ticketType":"STANDARD"},{"id":"3658","name":"City Center 15: Cinema de Lux","address":"19 Mamaroneck Ave.","city":"White Plains","state":"NY","zip":"10601","distance":"16.94852638244629","lon":"-73.765701","lat":"41.032177","theaterChainName":"National Amusements","ticketType":"STANDARD"},{"id":"2858","name":"Greenburgh Multiplex Cinemas","address":"320 Saw Mill River Road","city":"Elmsford","state":"NY","zip":"10523","distance":"13.555405616760254","lon":"-73.812698","lat":"41.066166","theaterChainName":"National Amusements","ticketType":"STANDARD"},{"id":"1523","name":"Regal Fishkill 10","address":"2400 Rt. 9","city":"Fishkill","state":"NY","zip":"12524","distance":"22.9227294921875","lon":"-73.896057","lat":"41.524448","theaterChainName":"Regal Cinemas","ticketType":"STANDARD"},{"id":"4603","name":"Downing Film Center","address":"19 Front Street","city":"Newburgh","state":"NY","zip":"12550","distance":"20.741962432861328","lon":"-74.005577","lat":"41.502258","theaterChainName":"Independent Chains","ticketType":"STANDARD"},{"id":"1848","name":"Destinta New Windsor 12","address":"215 Quassaik Ave.","city":"New Windsor","state":"NY","zip":"12553","distance":"18.93124771118164","lon":"-74.022850","lat":"41.475563","theaterChainName":"Independent Chains","ticketType":"STANDARD"},{"id":"3953","name":"Showtime Cinemas - Newburgh","address":"1420 Route 300","city":"Newburgh","state":"NY","zip":"12550","distance":"22.54124641418457","lon":"-74.070198","lat":"41.524101","theaterChainName":"Independent Chains","ticketType":"STANDARD"},{"id":"1529","name":"Bow Tie Cinemas Cinema 100","address":"93 Knollwood Road","city":"White Plains","state":"NY","zip":"10607","distance":"15.109737396240234","lon":"-73.808197","lat":"41.038300","theaterChainName":"Bow-Tie Cinemas","ticketType":"STANDARD"},{"id":"119","name":"Bow Tie Cinemas Mamaroneck 4","address":"243 Mamaroneck Ave.","city":"Mamaroneck","state":"NY","zip":"10543","distance":"22.247756958007812","lon":"-73.733871","lat":"40.950565","theaterChainName":"Bow-Tie Cinemas","ticketType":"STANDARD"},{"id":"5208","name":"Alamo Drafthouse Yonkers","address":"2548 Central Park Ave","city":"Yonkers","state":"NY","zip":"10710","distance":"17.723188400268555","lon":"-73.824547","lat":"40.982544","theaterChainName":"Alamo Drafthouse","ticketType":"STANDARD"},{"id":"771","name":"AMC Loews Palisades Center 21","address":"4403 Palisades Center Drive","city":"West Nyack","state":"NY","zip":"10994","distance":"7.5639424324035645","lon":"-73.956482","lat":"41.097771","theaterChainName":"AMC Theatres","ticketType":"STANDARD"},{"id":"1494","name":"Bow Tie Cinemas New City Cinema 6","address":"202 S. Main St.","city":"New City","state":"NY","zip":"10956","distance":"4.361266136169434","lon":"-73.989021","lat":"41.139576","theaterChainName":"Bow-Tie Cinemas","ticketType":"STANDARD"},{"id":"118","name":"Bow Tie Cinemas Larchmont Playhouse","address":"1975 Palmer Ave.","city":"Larchmont","state":"NY","zip":"10538","distance":"22.501075744628906","lon":"-73.761002","lat":"40.931107","theaterChainName":"Bow-Tie Cinemas","ticketType":"STANDARD"},{"id":"2584","name":"Regal New Roc Stadium 18 + IMAX","address":"33 Le Count Place","city":"New Rochelle","state":"NY","zip":"10801","distance":"23.11762237548828","lon":"-73.779564","lat":"40.911964","theaterChainName":"Regal Cinemas","ticketType":"STANDARD"},{"id":"5044","name":"Showcase Cinema de Lux Ridge Hill","address":"29 Fitzgerald St.","city":"Yonkers","state":"NY","zip":"10710","distance":"18.388460159301758","lon":"-73.844398","lat":"40.963402","theaterChainName":"National Amusements","ticketType":"STANDARD"},{"id":"117","name":"Bow Tie Cinemas Bronxville 3","address":"84 Kraft Ave.","city":"Bronxville","state":"NY","zip":"10708","distance":"20.054397583007812","lon":"-73.834435","lat":"40.940258","theaterChainName":"Bow-Tie Cinemas","ticketType":"STANDARD"},{"id":"1178","name":"Pelham Picture House","address":"175 Wolfs Lane","city":"Pelham","state":"NY","zip":"10803","distance":"22.627199172973633","lon":"-73.811378","lat":"40.907318","theaterChainName":"Independent Chains","ticketType":"STANDARD"},{"id":"282","name":"Cross County Multiplex Cinemas","address":"2 South Drive","city":"Yonkers","state":"NY","zip":"10704","distance":"20.614564895629883","lon":"-73.854446","lat":"40.924828","theaterChainName":"National Amusements","ticketType":"STANDARD"},{"id":"562","name":"AMC Bay Plaza Cinema 13","address":"2210 Bartow Ave.","city":"Bronx","state":"NY","zip":"10475","distance":"24.893909454345703","lon":"-73.825142","lat":"40.866989","theaterChainName":"AMC Theatres","ticketType":"STANDARD"},{"id":"4888","name":"Fabian 8 Cinema","address":"301 Main St.","city":"Paterson","state":"NJ","zip":"07505","distance":"21.79745864868164","lon":"-74.173370","lat":"40.914829","theaterChainName":"Independent Chains","ticketType":"STANDARD"},{"id":"1173","name":"Hawthorne 5","address":"300 Lafayette Ave.","city":"Hawthorne","state":"NJ","zip":"07506","distance":"19.29107093811035","lon":"-74.155380","lat":"40.948498","theaterChainName":"Independent Chains","ticketType":"STANDARD"},{"id":"4336","name":"AMC Garden State 16","address":"4000 Garden State Plaza","city":"Paramus","state":"NJ","zip":"07652","distance":"19.97901153564453","lon":"-74.075958","lat":"40.918610","theaterChainName":"AMC Theatres","ticketType":"STANDARD"},{"id":"407","name":"Bow Tie Cinemas Wayne Preakness","address":"1220 Hamburg Tpk.","city":"Wayne","state":"NJ","zip":"07470","distance":"20.912715911865234","lon":"-74.244293","lat":"40.961617","theaterChainName":"Bow-Tie Cinemas","ticketType":"STANDARD"},{"id":"5401","name":"Starplex Cinemas Ridgefield Park","address":"75 Challenger Road","city":"Ridgefield Park","state":"NJ","zip":"07660","distance":"24.318153381347656","lon":"-74.012550","lat":"40.850277","theaterChainName":"Starplex Cinemas","ticketType":"STANDARD"},{"id":"179","name":"Bow Tie Cinemas Warner Quad","address":"190 E. Ridgewood Ave.","city":"Ridgewood","state":"NJ","zip":"07450","distance":"16.546300888061523","lon":"-74.115486","lat":"40.978867","theaterChainName":"Bow-Tie Cinemas","ticketType":"STANDARD"},{"id":"6041","name":"Kinnelon Cinemas","address":"25 Kinnelon Rd","city":"Kinnelon","state":"NJ","zip":"07405","distance":"23.279376983642578","lon":"-74.360992","lat":"41.002808","theaterChainName":"Independent Chains","ticketType":"STANDARD"},{"id":"1779","name":"Bow Tie Cinemas Kinnelon 11","address":"25 Kinnelon Road","city":"Kinnelon","state":"NJ","zip":"07405","distance":"23.274532318115234","lon":"-74.360992","lat":"41.002926","theaterChainName":"Bow-Tie Cinemas","ticketType":"STANDARD"},{"id":"6036","name":"Washington Township Cinemas","address":"249 Pascack Road","city":"Washington Township","state":"NJ","zip":"07676","distance":"15.36581802368164","lon":"-74.063202","lat":"40.984798","theaterChainName":"Independent Chains","ticketType":"STANDARD"},{"id":"1495","name":"Lafayette Theatre","address":"97 Lafayette Ave.","city":"Suffern","state":"NY","zip":"10901","distance":"9.845765113830566","lon":"-74.150352","lat":"41.115063","theaterChainName":"Boston Culinary Group","ticketType":"STANDARD"},{"id":"1147","name":"Bow Tie Cinemas Tenafly Cinema 4","address":"4 1\/2 W. Railroad Ave.","city":"Tenafly","state":"NJ","zip":"07670","distance":"19.295839309692383","lon":"-73.965164","lat":"40.924118","theaterChainName":"Bow-Tie Cinemas","ticketType":"STANDARD"},{"id":"1766","name":"Bow Tie Cinemas Bergenfield 5 ","address":"58 S Washington Ave.","city":"Bergenfield","state":"NJ","zip":"07621","distance":"19.086219787597656","lon":"-73.996780","lat":"40.925892","theaterChainName":"Bow-Tie Cinemas","ticketType":"STANDARD"},{"id":"1131","name":"Bow Tie Cinemas Closter Cinema 4","address":"130 Closter Plaza","city":"Closter","state":"NJ","zip":"07624","distance":"16.305952072143555","lon":"-73.954964","lat":"40.968624","theaterChainName":"Bow-Tie Cinemas","ticketType":"STANDARD"},{"id":"160","name":"Westwood Theaters","address":"182 Center Ave.","city":"Westwood","state":"NJ","zip":"07675","distance":"14.674989700317383","lon":"-74.031570","lat":"40.991013","theaterChainName":"Independent Chains","ticketType":"STANDARD"},{"id":"5393","name":"Regal Nanuet Mall Stadium 12 & RPX","address":"6201 Fashion Dr.","city":"Nanuet","state":"NY","zip":"10954","distance":"7.247166156768799","lon":"-74.015152","lat":"41.097797","theaterChainName":"Regal Cinemas","ticketType":"STANDARD"},{"id":"5730","name":"Monroe Theaters at TMACC","address":"34 Millpond Parkway","city":"Monroe","state":"NY","zip":"10950","distance":"13.023248672485352","lon":"-74.188400","lat":"41.326900","theaterChainName":"Independent Chains","ticketType":"STANDARD"},{"id":"2845","name":"Elite Cinema 6","address":"78 Brookside Ave.","city":"Chester","state":"NY","zip":"10918","distance":"18.326955795288086","lon":"-74.283905","lat":"41.360188","theaterChainName":"Independent Chains","ticketType":"STANDARD"}]