[{"id":"5635","name":"Cinebowl Grille + IMAX","address":"1614 S. Main St.","city":"Blacksburg","state":"VA","zip":"24060","distance":"22.195798873901367","lon":"-80.401283","lat":"37.211479","theaterChainName":"Frank Theatres","ticketType":"STANDARD"},{"id":"2421","name":"Lyric Theatre Blacksburg","address":"135 College Ave.","city":"Blacksburg","state":"VA","zip":"24060","distance":"23.614055633544922","lon":"-80.415657","lat":"37.230129","theaterChainName":"Independent Chains","ticketType":"STANDARD"},{"id":"4340","name":"Regal New River Valley Stadium 14","address":"110 New River Road","city":"Christiansburg","state":"VA","zip":"24073","distance":"19.34410285949707","lon":"-80.428696","lat":"37.163742","theaterChainName":"Regal Cinemas","ticketType":"STANDARD"},{"id":"2423","name":"Radford Theatre","address":"1043 Norwood Street","city":"Radford","state":"VA","zip":"24141","distance":"21.112489700317383","lon":"-80.555824","lat":"37.140900","theaterChainName":"Independent Chains","ticketType":"STANDARD"},{"id":"4700","name":"Hollywood Cinema","address":"6 Hollywood Blvd.","city":"Martinsville","state":"VA","zip":"24112","distance":"24.333032608032227","lon":"-79.967979","lat":"36.692902","theaterChainName":"Independent Chains","ticketType":"STANDARD"},{"id":"2424","name":"Radford Plaza Cinema Twin","address":"7472 Lee Highway","city":"Radford","state":"VA","zip":"24141","distance":"22.004310607910156","lon":"-80.579475","lat":"37.142551","theaterChainName":"Independent Chains","ticketType":"STANDARD"}]