[{"id":"3948","tribuneTheaterId":"3203","providerTheaterId":"","name":"Marquee Wakefield 12","address":"10600 Common Oaks Drive","city":"Raleigh","state":"NC","zip":"27614","distance":11.805496030802,"lon":"-78.542397","lat":"35.942403","theaterChainName":"Marquee Cinemas","ticketType":"STANDARD"},{"id":"2033","tribuneTheaterId":"1836","providerTheaterId":"","name":"Market Place Cinema","address":"907 W Beckford Dr","city":"Henderson","state":"NC","zip":"27536","distance":16.427000029961,"lon":"-78.431429","lat":"36.332847","theaterChainName":"Independent Chains","ticketType":"STANDARD"},{"id":"1039","tribuneTheaterId":"1907","providerTheaterId":"","name":"Six Forks Station Cinema","address":"9500 Forum Drive","city":"Raleigh","state":"NC","zip":"27615","distance":17.923367751352,"lon":"-78.656054","lat":"35.897707","theaterChainName":"Independent Chains","ticketType":"STANDARD"},{"id":"1259","tribuneTheaterId":"4759","providerTheaterId":"","name":"Carmike 15 Raleigh","address":"5501 Atlantic Springs Rd.","city":"Raleigh","state":"NC","zip":"27616","distance":18.387618300219,"lon":"-78.597307","lat":"35.858136","theaterChainName":"Carmike Cinemas","ticketType":"STANDARD"},{"id":"3926","tribuneTheaterId":"5633","providerTheaterId":"","name":"Regal Movies at North Hills 14","address":"4150 Main at North Hills St.","city":"Raleigh","state":"NC","zip":"27609","distance":20.929549404032,"lon":"-78.6431","lat":"35.8367","theaterChainName":"Regal Cinemas","ticketType":"STANDARD"},{"id":"4596","tribuneTheaterId":"9763","providerTheaterId":"","name":"Raleigh Grande 16","address":"4840 Grove Barton Rd","city":"Raleigh","state":"NC","zip":"27613","distance":21.514798371799,"lon":"-78.716612","lat":"35.872051","theaterChainName":"Carolina Cinemas","ticketType":"STANDARD"},{"id":"1038","tribuneTheaterId":"229","providerTheaterId":"","name":"Rialto Theatre","address":"1620 Glenwood Ave","city":"Raleigh","state":"NC","zip":"27608","distance":23.009016789821,"lon":"-78.645461","lat":"35.803095","theaterChainName":"Independent Chains","ticketType":"STANDARD"},{"id":"3612","tribuneTheaterId":"7015","providerTheaterId":"","name":"Regal Brier Creek Stadium 14","address":"8611 Brier Creek Pkwy","city":"Raleigh","state":"NC","zip":"27617","distance":22.974586488683,"lon":"-78.78479","lat":"35.904211","theaterChainName":"Regal Cinemas","ticketType":"STANDARD"}]