[{"id":"3147","tribuneTheaterId":"3232","providerTheaterId":"","name":"Carmike Crossroads 16","address":"1536 Dogwood Dr.","city":"Conyers","state":"GA","zip":"30013","distance":7.8640921421663,"lon":"-83.994759","lat":"33.649084","theaterChainName":"Carmike Cinemas","ticketType":"STANDARD"},{"id":"3500","tribuneTheaterId":"4252","providerTheaterId":"707","name":"AMC Stonecrest 16","address":"8060 Mall Parkway","city":"Lithonia","state":"GA","zip":"30038","distance":14.064009023712,"lon":"-84.0916","lat":"33.6923","theaterChainName":"AMC Theatres","ticketType":"STANDARD"},{"id":"4138","tribuneTheaterId":"7488","providerTheaterId":"","name":"Great Escape McDonough","address":"115 Fosters Drive","city":"McDonough","state":"GA","zip":"30253","distance":19.541416205574,"lon":"-84.210259","lat":"33.46654","theaterChainName":"Regal Cinemas","ticketType":"STANDARD"},{"id":"422","tribuneTheaterId":"6911","providerTheaterId":"","name":"Regal Snellville Oaks Stadium 14","address":"2125 E.  Main St.","city":"Snellville","state":"GA","zip":"30078","distance":20.68257039175,"lon":"-84.002618","lat":"33.85687","theaterChainName":"Regal Cinemas","ticketType":"STANDARD"},{"id":"452","tribuneTheaterId":"3174","providerTheaterId":"","name":"Carmike 12 Snellville","address":"1905 Scenic Highway","city":"Snellville","state":"GA","zip":"30078","distance":22.216424182778,"lon":"-84.014747","lat":"33.876956","theaterChainName":"Carmike Cinemas","ticketType":"STANDARD"},{"id":"5576","tribuneTheaterId":"11024","providerTheaterId":"","name":"NCG Stone Mountain","address":"1825 Rockbridge Road","city":"Stone Mountain","state":"GA","zip":"30087","distance":21.923588427942,"lon":"-84.1232","lat":"33.8255","theaterChainName":"NCG Cinemas","ticketType":"STANDARD"},{"id":"6047","tribuneTheaterId":"11450","providerTheaterId":"","name":"AMC Dine-in Webb Gin 11","address":"1210 Scenic Highway","city":"Lawrenceville","state":"GA","zip":"30045","distance":23.769992526284,"lon":"-84.000945","lat":"33.903777","theaterChainName":"AMC Theatres","ticketType":"STANDARD"},{"id":"5908","tribuneTheaterId":"11332","providerTheaterId":"","name":"Satellite Cinemas South Dekalb","address":"2801 Candler Road #68","city":"Decatur","state":"GA","zip":"30034","distance":23.767259667759,"lon":"-84.274022","lat":"33.708345","theaterChainName":"Independent Chains","ticketType":"STANDARD"}]