[{"id":"379","name":"AMC North Dekalb Mall 16","address":"2042 Lawrenceville Hwy","city":"Decatur","state":"GA","zip":"30033","distance":"21.606075286865234","lon":"-84.278419","lat":"33.807449","theaterChainName":"AMC Theatres","ticketType":"STANDARD"},{"id":"5908","name":"Satellite Cinemas South Dekalb","address":"2801 Candler Road #68","city":"Decatur","state":"GA","zip":"30034","distance":"15.021002769470215","lon":"-84.274025","lat":"33.708344","theaterChainName":"Independent Chains","ticketType":"STANDARD"},{"id":"4502","name":"Northlake Festival Movie Tavern","address":"4043 La Vista Rd","city":"Tucker","state":"GA","zip":"30084","distance":"24.332794189453125","lon":"-84.251503","lat":"33.842918","theaterChainName":"Movie Tavern","ticketType":"STANDARD"},{"id":"4253","name":"Plaza Theatre - Atlanta","address":"1049 Ponce De Leon Aveue N.E.","city":"Atlanta","state":"GA","zip":"30306","distance":"18.845909118652344","lon":"-84.353073","lat":"33.773441","theaterChainName":"Independent Chains","ticketType":"STANDARD"},{"id":"424","name":"Regal Tara Cinemas-Atlanta","address":"2345 Cheshire Bridge Rd NE","city":"Atlanta","state":"GA","zip":"30324","distance":"21.99527931213379","lon":"-84.350479","lat":"33.819023","theaterChainName":"Regal Cinemas","ticketType":"STANDARD"},{"id":"1143","name":"Cinefest Theatre","address":"66 Courtland Ave","city":"Atlanta","state":"GA","zip":"30303","distance":"17.831228256225586","lon":"-84.390404","lat":"33.756699","theaterChainName":"Independent Chains","ticketType":"STANDARD"},{"id":"378","name":"AMC Phipps Plaza 14","address":"3500 Peachtree Road N.E.","city":"Atlanta","state":"GA","zip":"30326","distance":"24.340282440185547","lon":"-84.362221","lat":"33.852844","theaterChainName":"AMC Theatres","ticketType":"STANDARD"},{"id":"4105","name":"Regal Atlantic Station Stadium 18","address":"261 19th St. NW","city":"Atlanta","state":"GA","zip":"30363","distance":"20.391124725341797","lon":"-84.396500","lat":"33.793400","theaterChainName":"Regal Cinemas","ticketType":"STANDARD"},{"id":"3500","name":"AMC Stonecrest 16","address":"8060 Mall Parkway","city":"Lithonia","state":"GA","zip":"30038","distance":"19.967241287231445","lon":"-84.091599","lat":"33.692299","theaterChainName":"AMC Theatres","ticketType":"STANDARD"},{"id":"582","name":"AMC Southlake 24","address":"7065 Mount Zion Circle","city":"Morrow","state":"GA","zip":"30260","distance":"4.502999305725098","lon":"-84.329315","lat":"33.563240","theaterChainName":"AMC Theatres","ticketType":"STANDARD"},{"id":"4425","name":"Movies ATL 14","address":"3760 Princeton Lakes Pkwy","city":"Atlanta","state":"GA","zip":"30331","distance":"14.496126174926758","lon":"-84.514374","lat":"33.660564","theaterChainName":"Carmike Cinemas","ticketType":"STANDARD"},{"id":"3147","name":"Carmike Crossroads 16","address":"1536 Dogwood Dr.","city":"Conyers","state":"GA","zip":"30013","distance":"22.944259643554688","lon":"-83.994759","lat":"33.649082","theaterChainName":"Carmike Cinemas","ticketType":"STANDARD"},{"id":"4138","name":"Great Escape McDonough","address":"115 Fosters Drive","city":"McDonough","state":"GA","zip":"30253","distance":"8.464240074157715","lon":"-84.210258","lat":"33.466541","theaterChainName":"Regal Cinemas","ticketType":"STANDARD"},{"id":"1411","name":"Cinemark Tinseltown 17 Fayetteville","address":"134 Pavilion Parkway","city":"Fayetteville","state":"GA","zip":"30214","distance":"5.595666408538818","lon":"-84.444656","lat":"33.478416","theaterChainName":"Cinemark","ticketType":"STANDARD"},{"id":"443","name":"Cinemark Movies 10 Fayetteville","address":"157 Banks Station","city":"Fayetteville","state":"GA","zip":"30214","distance":"5.884151458740234","lon":"-84.444695","lat":"33.466286","theaterChainName":"Cinemark","ticketType":"STANDARD"},{"id":"4467","name":"Griffin Stadium Cinemas","address":"1367 North Expressway","city":"Griffin","state":"GA","zip":"30223","distance":"16.317453384399414","lon":"-84.294655","lat":"33.269337","theaterChainName":"Georgia Theatre Company","ticketType":"STANDARD"},{"id":"748","name":"Carmike 10 Newnan","address":"87 Newnan Station Drive","city":"Newnan","state":"GA","zip":"30265","distance":"23.25253677368164","lon":"-84.734810","lat":"33.396538","theaterChainName":"Carmike Cinemas","ticketType":"STANDARD"},{"id":"5028","name":"NCG Sharpsburg","address":"55  Fischer Crossings Blvd.","city":"Sharpsburg","state":"GA","zip":"30277","distance":"18.966686248779297","lon":"-84.655998","lat":"33.397202","theaterChainName":"NCG Cinemas","ticketType":"STANDARD"}]