[{"id":"373","name":"AMC Regency - 20","address":"2496 Brandon Blvd","city":"Brandon","state":"FL","zip":"33511","distance":"6.829730033874512","lon":"-82.324448","lat":"27.943275","theaterChainName":"AMC Theatres","ticketType":"STANDARD"},{"id":"6043","name":"Xscape Riverview 14","address":"6135 Valleydale Dr.","city":"Riverview","state":"FL","zip":"33578","distance":"3.886256694793701","lon":"-82.344475","lat":"27.893623","theaterChainName":"Independent Chains","ticketType":"STANDARD"},{"id":"5972","name":"Riverview 14 GDX","address":"10550 East Bay Road","city":"Gibsonton","state":"FL","zip":"33534","distance":"2.219554901123047","lon":"-82.348618","lat":"27.848459","theaterChainName":"Goodrich Theatres","ticketType":"SELECT_SEATING"},{"id":"3090","name":"Muvico Centro Ybor 20","address":"1600 East 8th Ave","city":"Tampa","state":"FL","zip":"33605","distance":"11.182018280029297","lon":"-82.440300","lat":"27.960899","theaterChainName":"Carmike Cinemas","ticketType":"STANDARD"},{"id":"870","name":"Tampa Theatre","address":"711 N. Franklin St.","city":"Tampa","state":"FL","zip":"33602","distance":"11.51386547088623","lon":"-82.458900","lat":"27.950001","theaterChainName":"Independent Chains","ticketType":"STANDARD"},{"id":"4537","name":"Plant City Premiere Cinema 8","address":"220 W. Alexander St.","city":"Plant City","state":"FL","zip":"33566","distance":"15.31411075592041","lon":"-82.123123","lat":"27.990320","theaterChainName":"Independent Chains","ticketType":"STANDARD"},{"id":"5564","name":"Studio Movie Grill Tampa","address":"12332 University Mall Court","city":"Tampa","state":"FL","zip":"33612","distance":"16.496274948120117","lon":"-82.435310","lat":"28.057667","theaterChainName":"Studio Movie Grill","ticketType":"SELECT_SEATING"},{"id":"2824","name":"Muvico Starlight 20","address":"18002 Highwood Preserve Pkwy","city":"Tampa","state":"FL","zip":"33647","distance":"20.04010772705078","lon":"-82.370361","lat":"28.130489","theaterChainName":"Carmike Cinemas","ticketType":"STANDARD"},{"id":"3099","name":"AMC West Shore Plaza 14","address":"210 Westshore Plaza","city":"Tampa","state":"FL","zip":"33609","distance":"14.850508689880371","lon":"-82.526665","lat":"27.946806","theaterChainName":"AMC Theatres","ticketType":"STANDARD"},{"id":"5351","name":"Villagio Cinemas","address":"11778 N. Dale Mabry Highway","city":"Tampa","state":"FL","zip":"33618","distance":"18.670427322387695","lon":"-82.503998","lat":"28.055700","theaterChainName":"Independent Chains","ticketType":"STANDARD"},{"id":"2563","name":"AMC Veterans 24","address":"9302 Anderson Rd.","city":"Tampa","state":"FL","zip":"33634","distance":"19.13644027709961","lon":"-82.542732","lat":"28.032961","theaterChainName":"AMC Theatres","ticketType":"STANDARD"},{"id":"4126","name":"Cobb Lakeside Village 18 & Imax","address":"1650 Town Center Drive","city":"Lakeland","state":"FL","zip":"33803","distance":"22.882707595825195","lon":"-81.981445","lat":"28.000261","theaterChainName":"Cobb Theatres","ticketType":"STANDARD"},{"id":"2283","name":"Regal Citrus Park Stadium 20","address":"7611 Ehrlich Rd","city":"Tampa","state":"FL","zip":"33625","distance":"22.327880859375","lon":"-82.575600","lat":"28.069519","theaterChainName":"Regal Cinemas","ticketType":"STANDARD"},{"id":"593","name":"Regal Citrus Cinemas 6","address":"2635 East Gulf To Lake Hwy","city":"Inverness","state":"FL","zip":"34453","distance":"22.34479331970215","lon":"-82.575760","lat":"28.069725","theaterChainName":"Regal Cinemas","ticketType":"STANDARD"},{"id":"1271","name":"Carmike Palm Cinema 3","address":"4226 Old Highway 37","city":"Lakeland","state":"FL","zip":"33813","distance":"23.663110733032227","lon":"-81.960419","lat":"27.988140","theaterChainName":"Carmike Cinemas","ticketType":"STANDARD"},{"id":"3100","name":"Muvico Baywalk 20","address":"151 2nd Ave North St.","city":"Saint Petersburg","state":"FL","zip":"33701","distance":"20.294933319091797","lon":"-82.634781","lat":"27.774220","theaterChainName":"Carmike Cinemas","ticketType":"STANDARD"},{"id":"3164","name":"Regal Cinemas Park Place Stadium 16 & RPX","address":"7200 US Highway 19 North","city":"Pinellas Park","state":"FL","zip":"33781","distance":"22.846628189086914","lon":"-82.686302","lat":"27.836515","theaterChainName":"Regal Cinemas","ticketType":"STANDARD"}]