[{"id":"595","tribuneTheaterId":"8725","providerTheaterId":"","name":"Regal Largo Mall 8","address":"10500 Ulmerton Rd East #500","city":"Largo","state":"FL","zip":"33771","distance":3.6680420769947,"lon":"-82.783625","lat":"27.891012","theaterChainName":"Regal Cinemas","ticketType":"STANDARD"},{"id":"4627","tribuneTheaterId":"9809","providerTheaterId":"","name":"Touchstar Cinemas - Seminole 8","address":"7990 Liberty Lane","city":"Seminole","state":"FL","zip":"33772","distance":4.30238905833,"lon":"-82.791746","lat":"27.844561","theaterChainName":"Touchstar Cinemas","ticketType":"STANDARD"},{"id":"5543","tribuneTheaterId":"10981","providerTheaterId":"","name":"Capitol Theater","address":"405 Cleveland Street","city":"Clearwater","state":"FL","zip":"33755","distance":6.0311420040099,"lon":"-82.801","lat":"27.9656","theaterChainName":"Independent Chains","ticketType":"STANDARD"},{"id":"5889","tribuneTheaterId":"11308","providerTheaterId":"","name":"Cobb Tyrone Luxury 10","address":"2998 Tyrone Blvd N.","city":"Saint Petersburg","state":"FL","zip":"33710","distance":9.0094071282394,"lon":"-82.7363","lat":"27.797259","theaterChainName":"Cobb Theatres","ticketType":"STANDARD"},{"id":"869","tribuneTheaterId":"6834","providerTheaterId":"","name":"Clearwater Cinema Cafe","address":"24095 U.S. Highway 19 North","city":"Clearwater","state":"FL","zip":"33763","distance":10.087794575589,"lon":"-82.727925","lat":"27.991162","theaterChainName":"Independent Chains","ticketType":"STANDARD"},{"id":"5098","tribuneTheaterId":"10494","providerTheaterId":"","name":"Cobb Countryside 12 Cinemas","address":"27001 US Highway 19 N.","city":"Clearwater","state":"FL","zip":"33761","distance":11.097400378498,"lon":"-82.737503","lat":"28.0173","theaterChainName":"Cobb Theatres","ticketType":"STANDARD"},{"id":"3164","tribuneTheaterId":"7890","providerTheaterId":"","name":"Regal Cinemas Park Place Stadium 16 & RPX","address":"7200 US Highway 19 North","city":"Pinellas Park","state":"FL","zip":"33781","distance":10.211416772624,"lon":"-82.686303","lat":"27.836516","theaterChainName":"Regal Cinemas","ticketType":"STANDARD"},{"id":"2970","tribuneTheaterId":"9166","providerTheaterId":"700","name":"AMC Woodlands Square 20","address":"3128 Tampa Road","city":"Oldsmar","state":"FL","zip":"34677","distance":14.375360403358,"lon":"-82.7004","lat":"28.052071","theaterChainName":"AMC Theatres","ticketType":"STANDARD"},{"id":"3100","tribuneTheaterId":"5851","providerTheaterId":"","name":"Muvico Baywalk 20","address":"151 2nd Ave North St.","city":"Saint Petersburg","state":"FL","zip":"33701","distance":14.937888284681,"lon":"-82.634784","lat":"27.77422","theaterChainName":"Carmike Cinemas","ticketType":"STANDARD"},{"id":"769","tribuneTheaterId":"6571","providerTheaterId":"","name":"Muvico Palm Harbor 10","address":"37912 US Highway 19N","city":"Palm Harbor","state":"FL","zip":"34684","distance":17.060558305488,"lon":"-82.741067","lat":"28.116561","theaterChainName":"Carmike Cinemas","ticketType":"STANDARD"},{"id":"3099","tribuneTheaterId":"5294","providerTheaterId":"701","name":"AMC West Shore Plaza 14","address":"210 Westshore Plaza","city":"Tampa","state":"FL","zip":"33609","distance":19.783104688418,"lon":"-82.526663","lat":"27.946806","theaterChainName":"AMC Theatres","ticketType":"STANDARD"},{"id":"2563","tribuneTheaterId":"9045","providerTheaterId":"273","name":"AMC Veterans 24","address":"9302 Anderson Rd.","city":"Tampa","state":"FL","zip":"33634","distance":20.950224976743,"lon":"-82.542729","lat":"28.032961","theaterChainName":"AMC Theatres","ticketType":"STANDARD"},{"id":"2283","tribuneTheaterId":"8795","providerTheaterId":"","name":"Regal Citrus Park Stadium 20","address":"7611 Ehrlich Rd","city":"Tampa","state":"FL","zip":"33625","distance":20.654102183686,"lon":"-82.575603","lat":"28.069519","theaterChainName":"Regal Cinemas","ticketType":"STANDARD"},{"id":"593","tribuneTheaterId":"8586","providerTheaterId":"","name":"Regal Citrus Cinemas 6","address":"2635 East Gulf To Lake Hwy","city":"Inverness","state":"FL","zip":"34453","distance":20.655311487382,"lon":"-82.575758","lat":"28.069725","theaterChainName":"Regal Cinemas","ticketType":"STANDARD"},{"id":"5351","tribuneTheaterId":"10788","providerTheaterId":"","name":"Villagio Cinemas","address":"11778 N. Dale Mabry Highway","city":"Tampa","state":"FL","zip":"33618","distance":23.777679455002,"lon":"-82.504","lat":"28.0557","theaterChainName":"Independent Chains","ticketType":"STANDARD"},{"id":"870","tribuneTheaterId":"6025","providerTheaterId":"","name":"Tampa Theatre","address":"711 N. Franklin St.","city":"Tampa","state":"FL","zip":"33602","distance":23.883149313964,"lon":"-82.4589","lat":"27.950001","theaterChainName":"Independent Chains","ticketType":"STANDARD"}]