[{"id":"769","tribuneTheaterId":"6571","providerTheaterId":"","name":"Muvico Palm Harbor 10","address":"37912 US Highway 19N","city":"Palm Harbor","state":"FL","zip":"34684","distance":5.2434789642906,"lon":"-82.741067","lat":"28.116561","theaterChainName":"Carmike Cinemas","ticketType":"STANDARD"},{"id":"596","tribuneTheaterId":"7138","providerTheaterId":"","name":"Regal Hollywood 18-Port Richey","address":"6701 Cinema Dr","city":"Port Richey","state":"FL","zip":"34668","distance":8.6496230936215,"lon":"-82.703497","lat":"28.307631","theaterChainName":"Regal Cinemas","ticketType":"STANDARD"},{"id":"4826","tribuneTheaterId":"10100","providerTheaterId":"","name":"Cinema 6 - Port Richey","address":"9510 US HWY 19","city":"Port Richey","state":"FL","zip":"34668","distance":7.73086481878,"lon":"-82.707288","lat":"28.294634","theaterChainName":"Independent Chains","ticketType":"STANDARD"},{"id":"2970","tribuneTheaterId":"9166","providerTheaterId":"700","name":"AMC Woodlands Square 20","address":"3128 Tampa Road","city":"Oldsmar","state":"FL","zip":"34677","distance":10.198994088108,"lon":"-82.7004","lat":"28.052071","theaterChainName":"AMC Theatres","ticketType":"STANDARD"},{"id":"5098","tribuneTheaterId":"10494","providerTheaterId":"","name":"Cobb Countryside 12 Cinemas","address":"27001 US Highway 19 N.","city":"Clearwater","state":"FL","zip":"33761","distance":12.074973989214,"lon":"-82.737503","lat":"28.0173","theaterChainName":"Cobb Theatres","ticketType":"STANDARD"},{"id":"593","tribuneTheaterId":"8586","providerTheaterId":"","name":"Regal Citrus Cinemas 6","address":"2635 East Gulf To Lake Hwy","city":"Inverness","state":"FL","zip":"34453","distance":13.826587308172,"lon":"-82.575758","lat":"28.069725","theaterChainName":"Regal Cinemas","ticketType":"STANDARD"},{"id":"869","tribuneTheaterId":"6834","providerTheaterId":"","name":"Clearwater Cinema Cafe","address":"24095 U.S. Highway 19 North","city":"Clearwater","state":"FL","zip":"33763","distance":13.933681436727,"lon":"-82.727925","lat":"27.991162","theaterChainName":"Independent Chains","ticketType":"STANDARD"},{"id":"2283","tribuneTheaterId":"8795","providerTheaterId":"","name":"Regal Citrus Park Stadium 20","address":"7611 Ehrlich Rd","city":"Tampa","state":"FL","zip":"33625","distance":13.842745554593,"lon":"-82.575603","lat":"28.069519","theaterChainName":"Regal Cinemas","ticketType":"STANDARD"},{"id":"5543","tribuneTheaterId":"10981","providerTheaterId":"","name":"Capitol Theater","address":"405 Cleveland Street","city":"Clearwater","state":"FL","zip":"33755","distance":15.833807587251,"lon":"-82.801","lat":"27.9656","theaterChainName":"Independent Chains","ticketType":"STANDARD"},{"id":"5351","tribuneTheaterId":"10788","providerTheaterId":"","name":"Villagio Cinemas","address":"11778 N. Dale Mabry Highway","city":"Tampa","state":"FL","zip":"33618","distance":17.98831204525,"lon":"-82.504","lat":"28.0557","theaterChainName":"Independent Chains","ticketType":"STANDARD"},{"id":"2563","tribuneTheaterId":"9045","providerTheaterId":"273","name":"AMC Veterans 24","address":"9302 Anderson Rd.","city":"Tampa","state":"FL","zip":"33634","distance":16.988645736298,"lon":"-82.542729","lat":"28.032961","theaterChainName":"AMC Theatres","ticketType":"STANDARD"},{"id":"597","tribuneTheaterId":"6272","providerTheaterId":"","name":"Spring Hill 8 Cinemas","address":"2955 Commercial Way","city":"Spring Hill","state":"FL","zip":"34606","distance":21.384570738301,"lon":"-82.61763","lat":"28.475832","theaterChainName":"Sapphire Motion Pictures Inc.","ticketType":"STANDARD"},{"id":"595","tribuneTheaterId":"8725","providerTheaterId":"","name":"Regal Largo Mall 8","address":"10500 Ulmerton Rd East #500","city":"Largo","state":"FL","zip":"33771","distance":20.816169856364,"lon":"-82.783625","lat":"27.891012","theaterChainName":"Regal Cinemas","ticketType":"STANDARD"},{"id":"3099","tribuneTheaterId":"5294","providerTheaterId":"701","name":"AMC West Shore Plaza 14","address":"210 Westshore Plaza","city":"Tampa","state":"FL","zip":"33609","distance":21.9285890641,"lon":"-82.526663","lat":"27.946806","theaterChainName":"AMC Theatres","ticketType":"STANDARD"},{"id":"5564","tribuneTheaterId":"11011","providerTheaterId":"","name":"Studio Movie Grill Tampa","address":"12332 University Mall Court","city":"Tampa","state":"FL","zip":"33612","distance":21.612786222652,"lon":"-82.43531","lat":"28.057667","theaterChainName":"Studio Movie Grill","ticketType":"SELECT_SEATING"},{"id":"2824","tribuneTheaterId":"5850","providerTheaterId":"","name":"Muvico Starlight 20","address":"18002 Highwood Preserve Pkwy","city":"Tampa","state":"FL","zip":"33647","distance":23.863827669655,"lon":"-82.37036","lat":"28.130489","theaterChainName":"Carmike Cinemas","ticketType":"STANDARD"},{"id":"3164","tribuneTheaterId":"7890","providerTheaterId":"","name":"Regal Cinemas Park Place Stadium 16 & RPX","address":"7200 US Highway 19 North","city":"Pinellas Park","state":"FL","zip":"33781","distance":24.879126414864,"lon":"-82.686303","lat":"27.836516","theaterChainName":"Regal Cinemas","ticketType":"STANDARD"},{"id":"870","tribuneTheaterId":"6025","providerTheaterId":"","name":"Tampa Theatre","address":"711 N. Franklin St.","city":"Tampa","state":"FL","zip":"33602","distance":24.617820145756,"lon":"-82.4589","lat":"27.950001","theaterChainName":"Independent Chains","ticketType":"STANDARD"},{"id":"3090","tribuneTheaterId":"7161","providerTheaterId":"","name":"Muvico Centro Ybor 20","address":"1600 East 8th Ave","city":"Tampa","state":"FL","zip":"33605","distance":24.976413894962,"lon":"-82.4403","lat":"27.9609","theaterChainName":"Carmike Cinemas","ticketType":"STANDARD"},{"id":"4627","tribuneTheaterId":"9809","providerTheaterId":"","name":"Touchstar Cinemas - Seminole 8","address":"7990 Liberty Lane","city":"Seminole","state":"FL","zip":"33772","distance":24.056353942338,"lon":"-82.791746","lat":"27.844561","theaterChainName":"Touchstar Cinemas","ticketType":"STANDARD"}]