[{"id":"2660","tribuneTheaterId":"4643","providerTheaterId":"","name":"Regal Cobblestone Square Stadium 20","address":"5500 Cobbleston Rd.","city":"Elyria","state":"OH","zip":"44035","distance":4.3548257716425,"lon":"-82.0787","lat":"41.4207","theaterChainName":"Regal Cinemas","ticketType":"STANDARD"},{"id":"4626","tribuneTheaterId":"9808","providerTheaterId":"","name":"Atlas Cinemas Midway Mall 8","address":"2650 Midway Mall Blvd.","city":"Elyria","state":"OH","zip":"44035","distance":6.0893408795091,"lon":"-82.111173","lat":"41.394857","theaterChainName":"Atlas Cinemas","ticketType":"STANDARD"},{"id":"643","tribuneTheaterId":"8411","providerTheaterId":"","name":"Regal Cinemas Crocker Park Stadium 16 & IMAX","address":"30147 Detroit Road","city":"Westlake","state":"OH","zip":"44145","distance":7.5843835754397,"lon":"-81.952665","lat":"41.461455","theaterChainName":"Regal Cinemas","ticketType":"STANDARD"},{"id":"5414","tribuneTheaterId":"10851","providerTheaterId":"","name":"Great Northern Mall Stadium 10 + RPX","address":"450 Great Northern Mall","city":"North Olmsted","state":"OH","zip":"44070","distance":10.640322265851,"lon":"-81.9095","lat":"41.4185","theaterChainName":"Regal Cinemas","ticketType":"STANDARD"},{"id":"759","tribuneTheaterId":"8247","providerTheaterId":"839","name":"AMC Westwood Town Center 6","address":"21653 Center Ridge Road","city":"Rocky River","state":"OH","zip":"44116","distance":12.335707241337,"lon":"-81.860459","lat":"41.457929","theaterChainName":"AMC Theatres","ticketType":"STANDARD"},{"id":"2026","tribuneTheaterId":"305","providerTheaterId":"","name":"Apollo","address":"19 East College Street","city":"Oberlin","state":"OH","zip":"44074","distance":14.578066982648,"lon":"-82.216715","lat":"41.291558","theaterChainName":"Cleveland Cinemas","ticketType":"STANDARD"},{"id":"641","tribuneTheaterId":"7416","providerTheaterId":"","name":"Regal Middlesburg Town Square Stadium 16","address":"18348 Bagley Road","city":"Middleburg Heights","state":"OH","zip":"44130","distance":15.672257175395,"lon":"-81.830528","lat":"41.374218","theaterChainName":"Regal Cinemas","ticketType":"STANDARD"},{"id":"757","tribuneTheaterId":"7068","providerTheaterId":"835","name":"AMC Ridge Park Square 8","address":"4788 Ridge Road","city":"Brooklyn","state":"OH","zip":"44144","distance":18.989016900051,"lon":"-81.73749","lat":"41.42633","theaterChainName":"AMC Theatres","ticketType":"STANDARD"},{"id":"4829","tribuneTheaterId":"10103","providerTheaterId":"","name":"Capitol Theatre - Cleveland","address":"1390 West 65th St.","city":"Cleveland","state":"OH","zip":"44102","distance":18.955342445714,"lon":"-81.730301","lat":"41.4842","theaterChainName":"Cleveland Cinemas","ticketType":"STANDARD"},{"id":"4329","tribuneTheaterId":"9304","providerTheaterId":"","name":"Cinemark Strongsville","address":"17450 Southpark Center","city":"Strongsville","state":"OH","zip":"44136","distance":18.574166870956,"lon":"-81.822031","lat":"41.309455","theaterChainName":"Cinemark","ticketType":"STANDARD"},{"id":"1075","tribuneTheaterId":"2279","providerTheaterId":"","name":"Tower City 11","address":"230 Huron Road","city":"Cleveland","state":"OH","zip":"44113","distance":20.875288117789,"lon":"-81.693631","lat":"41.496893","theaterChainName":"Cleveland Cinemas","ticketType":"STANDARD"},{"id":"758","tribuneTheaterId":"5180","providerTheaterId":"","name":"Hickory Ridge Cinemas 8","address":"1055 Pearl Road","city":"Brunswick","state":"OH","zip":"44212","distance":21.077431118687,"lon":"-81.839701","lat":"41.245839","theaterChainName":"Independent Chains","ticketType":"STANDARD"}]