[{"id":"645","name":"Encore Cinema","address":"930 Great East Plaza","city":"Niles","state":"OH","zip":"44446","distance":"22.147132873535156","lon":"-80.746841","lat":"41.213623","theaterChainName":"Independent Chains","ticketType":"STANDARD"},{"id":"644","name":"Regal Boulevard Center Stadium 14","address":"24 Boulevard Centre","city":"Niles","state":"OH","zip":"44446","distance":"21.840290069580078","lon":"-80.748314","lat":"41.217937","theaterChainName":"Regal Cinemas","ticketType":"STANDARD"},{"id":"2786","name":"Garrettsville Cinema","address":"8001 State Street","city":"Garrettsville","state":"OH","zip":"44231","distance":"22.11879539489746","lon":"-81.100502","lat":"41.287510","theaterChainName":"Independent Chains","ticketType":"STANDARD"},{"id":"2234","name":"Carmike Ashtabula Mall 6","address":"3315 N Ridge East Unit 400","city":"Ashtabula","state":"OH","zip":"44004","distance":"24.413082122802734","lon":"-80.753304","lat":"41.879002","theaterChainName":"Carmike Cinemas","ticketType":"STANDARD"}]