[{"id":"2439","name":"Central States Capitol II","address":"116 1st Street","city":"Newton","state":"IA","zip":"50208","distance":"9.979079246520996","lon":"-93.053505","lat":"41.700085","theaterChainName":"Independent Chains","ticketType":"STANDARD"},{"id":"4669","name":"Strand Theatre - Grinnell","address":"921 Main St.","city":"Grinnell","state":"IA","zip":"50112","distance":"13.165825843811035","lon":"-92.725830","lat":"41.743927","theaterChainName":"Fridley Theatres","ticketType":"STANDARD"}]