[{"id":"2118","tribuneTheaterId":"4016","providerTheaterId":"","name":"Vista 3 Theatres","address":"712 Lake Ave.","city":"Storm Lake","state":"IA","zip":"50588","distance":12.568769181621,"lon":"-95.201034","lat":"42.646004","theaterChainName":"Fridley Theatres","ticketType":"STANDARD"},{"id":"2102","tribuneTheaterId":"341","providerTheaterId":"","name":"American Theatre - Cherokee","address":"108 East Main Street","city":"Cherokee","state":"IA","zip":"51012","distance":20.243820334931,"lon":"-95.550688","lat":"42.749759","theaterChainName":"Fridley Theatres","ticketType":"STANDARD"},{"id":"4472","tribuneTheaterId":"9560","providerTheaterId":"","name":"Southpark 7 Theatre","address":"901 SW. 11th St.","city":"Spencer","state":"IA","zip":"51301","distance":20.862716111612,"lon":"-95.15733","lat":"43.127895","theaterChainName":"Fridley Theatres","ticketType":"STANDARD"}]