[{"id":"4552","name":"Mindframe Theaters","address":"555 JFK Rd","city":"Dubuque","state":"IA","zip":"52002","distance":"19.459178924560547","lon":"-90.724670","lat":"42.496277","theaterChainName":"Independent Chains","ticketType":"STANDARD"},{"id":"4324","name":"AMC Star Dubuque 14","address":"2835 N.W. Arterial","city":"Dubuque","state":"IA","zip":"52002","distance":"19.82815170288086","lon":"-90.737602","lat":"42.521099","theaterChainName":"AMC Theatres","ticketType":"STANDARD"},{"id":"2942","name":"Avalon Cinema","address":"95 E. Main St.","city":"Platteville","state":"WI","zip":"53818","distance":"13.851560592651367","lon":"-90.474297","lat":"42.733200","theaterChainName":"Independent Chains","ticketType":"STANDARD"}]