[{"id":"4044","name":"B&B Lexington Cannonball 6 Cinema","address":"1125 Franklin","city":"Lexington","state":"MO","zip":"64067","distance":"19.004783630371094","lon":"-93.882378","lat":"39.184364","theaterChainName":"B&B Theatres","ticketType":"STANDARD"},{"id":"4754","name":"Carmike 10 Warrensburg","address":"386 Hawthorne Blvd","city":"Warrensburg","state":"MO","zip":"64093","distance":"24.50337028503418","lon":"-93.733055","lat":"38.782494","theaterChainName":"Carmike Cinemas","ticketType":"STANDARD"},{"id":"1981","name":"Marshall Cinema - Marshall, MO","address":"114-120 E North Street","city":"Marshall","state":"MO","zip":"65340","distance":"18.69656753540039","lon":"-93.194809","lat":"39.121197","theaterChainName":"Independent Chains","ticketType":"STANDARD"}]