[{"id":"545","tribuneTheaterId":"7501","providerTheaterId":"610","name":"AMC Studio 30 Olathe","address":"12075 S Strang Line Rd.","city":"Olathe","state":"KS","zip":"66062","distance":15.657614439915,"lon":"-94.77","lat":"38.9099","theaterChainName":"AMC Theatres","ticketType":"STANDARD"},{"id":"940","tribuneTheaterId":"6827","providerTheaterId":"","name":"Regal Southwind Cinema 12","address":"3433 Iowa Street","city":"Lawrence","state":"KS","zip":"66046","distance":16.74400621256,"lon":"-95.262891","lat":"38.921658","theaterChainName":"Regal Cinemas","ticketType":"STANDARD"},{"id":"957","tribuneTheaterId":"2674","providerTheaterId":"","name":"Liberty Hall Cinema","address":"644 Massachussets Street","city":"Lawrence","state":"KS","zip":"66044","distance":17.918114024659,"lon":"-95.235744","lat":"38.971372","theaterChainName":"Independent Chains","ticketType":"STANDARD"},{"id":"5007","tribuneTheaterId":"10379","providerTheaterId":"","name":"Crystal Plaza","address":"209 S Main Street","city":"Ottawa","state":"KS","zip":"66067","distance":18.058864448655,"lon":"-95.2685","lat":"38.6155","theaterChainName":"Independent Chains","ticketType":"STANDARD"},{"id":"939","tribuneTheaterId":"5969","providerTheaterId":"","name":"B&B Shawnee 18","address":"16301 Midland Drive","city":"Shawnee","state":"KS","zip":"66217","distance":19.573244353819,"lon":"-94.775759","lat":"38.99831","theaterChainName":"B&B Theatres","ticketType":"STANDARD"},{"id":"3929","tribuneTheaterId":"5053","providerTheaterId":"","name":"B&B Overland Park 16","address":"8601 W. 135th Street","city":"Overland Park","state":"KS","zip":"66223","distance":18.847830693401,"lon":"-94.683748","lat":"38.881395","theaterChainName":"B&B Theatres","ticketType":"STANDARD"},{"id":"5519","tribuneTheaterId":"10945","providerTheaterId":"","name":"Cinetopia Overland Park 18","address":"5725 W. 135th St.","city":"Overland Park","state":"KS","zip":"66223","distance":20.495409197802,"lon":"-94.651551","lat":"38.882511","theaterChainName":"Independent Chains","ticketType":"STANDARD"},{"id":"543","tribuneTheaterId":"7973","providerTheaterId":"38","name":"AMC Town Center 20","address":"11701 Nall Ave.","city":"Leawood","state":"KS","zip":"66211","distance":21.554071634298,"lon":"-94.648118","lat":"38.915815","theaterChainName":"AMC Theatres","ticketType":"STANDARD"},{"id":"3042","tribuneTheaterId":"2603","providerTheaterId":"","name":"Rio Theatre - Overland Park","address":"7204 W. 80th St.","city":"Overland Park","state":"KS","zip":"66204","distance":23.053699195103,"lon":"-94.669288","lat":"38.984163","theaterChainName":"Independent Chains","ticketType":"STANDARD"},{"id":"2078","tribuneTheaterId":"5224","providerTheaterId":"","name":"Cinemark 20 and XD Merriam","address":"5500 Antioch","city":"Merriam","state":"KS","zip":"66202","distance":24.314817758742,"lon":"-94.687943","lat":"39.028619","theaterChainName":"Cinemark","ticketType":"STANDARD"},{"id":"3580","tribuneTheaterId":"659","providerTheaterId":"","name":"Glenwood Arts Theatre","address":"3707 W 95th St.","city":"Overland Park","state":"KS","zip":"66212","distance":23.788631513421,"lon":"-94.628879","lat":"38.956503","theaterChainName":"Independent Chains","ticketType":"STANDARD"}]