[{"id":"3522","tribuneTheaterId":"3165","providerTheaterId":"","name":"13th Avenue Warren","address":"11611 East 13th St.","city":"Wichita","state":"KS","zip":"67206","distance":3.3164409918714,"lon":"-97.20294","lat":"37.705663","theaterChainName":"Independent Chains","ticketType":"STANDARD"},{"id":"6104","tribuneTheaterId":"11518","providerTheaterId":"","name":"Warren Old Town Theatre & Grill","address":"353 N Mead","city":"Wichita","state":"KS","zip":"67202","distance":5.5007571303229,"lon":"-97.329347","lat":"37.691134","theaterChainName":"Independent Chains","ticketType":"STANDARD"},{"id":"3641","tribuneTheaterId":"1875","providerTheaterId":"","name":"Old Town Cinema Grill","address":"353 N. Mead","city":"Wichita","state":"KS","zip":"67202","distance":5.5031468877436,"lon":"-97.329","lat":"37.6907","theaterChainName":"Independent Chains","ticketType":"STANDARD"},{"id":"1931","tribuneTheaterId":"4159","providerTheaterId":"","name":"West Warren Theatre","address":"9150 W. 21st St. N.","city":"Wichita","state":"KS","zip":"67205","distance":10.968769915891,"lon":"-97.44789","lat":"37.724311","theaterChainName":"Independent Chains","ticketType":"STANDARD"},{"id":"2690","tribuneTheaterId":"2040","providerTheaterId":"","name":"Derby Plaza Theatre","address":"1300 North Nelson Drive","city":"Derby","state":"KS","zip":"67037","distance":12.439743086059,"lon":"-97.273523","lat":"37.559004","theaterChainName":"Independent Chains","ticketType":"STANDARD"},{"id":"2688","tribuneTheaterId":"451","providerTheaterId":"","name":"Augusta Theatre","address":"523 State Street","city":"Augusta","state":"KS","zip":"67010","distance":15.282058420818,"lon":"-96.9791","lat":"37.6771","theaterChainName":"Independent Chains","ticketType":"STANDARD"},{"id":"4354","tribuneTheaterId":"9372","providerTheaterId":"","name":"Chisholm Trail 8","address":"601 SE 36th Street 113","city":"Newton","state":"KS","zip":"67114","distance":18.537577197014,"lon":"-97.334219","lat":"37.9974","theaterChainName":"Mitchell Theatres","ticketType":"STANDARD"},{"id":"3706","tribuneTheaterId":"1980","providerTheaterId":"","name":"Central Cinema 6","address":"300 East Central","city":"El Dorado","state":"KS","zip":"67042","distance":22.609771073001,"lon":"-96.846494","lat":"37.818053","theaterChainName":"Mitchell Theatres","ticketType":"STANDARD"}]