[{"id":"1742","tribuneTheaterId":"275","providerTheaterId":"","name":"Vermillion Theatre","address":"4 W. Main St.","city":"Vermillion","state":"SD","zip":"57069","distance":6.6247828420211,"lon":"-96.931999","lat":"42.7794","theaterChainName":"Independent Chains","ticketType":"STANDARD"},{"id":"1986","tribuneTheaterId":"1134","providerTheaterId":"","name":"Coyote Theatre","address":"10 E. Main St.","city":"Vermillion","state":"SD","zip":"57069","distance":6.6263515569517,"lon":"-96.93193","lat":"42.779404","theaterChainName":"Independent Chains","ticketType":"STANDARD"}]