[{"id":"1691","tribuneTheaterId":"5707","providerTheaterId":"","name":"United Artists Regency Theatre","address":"635 Fairfield Drive","city":"Merced","state":"CA","zip":"95340","distance":9.1092900845015,"lon":"-120.47999","lat":"37.320501","theaterChainName":"United Artists","ticketType":"STANDARD"},{"id":"3195","tribuneTheaterId":"5135","providerTheaterId":"","name":"Regal Hollywood Merced 13","address":"403 W Main St","city":"Merced","state":"CA","zip":"95340","distance":9.0088741115955,"lon":"-120.481889","lat":"37.301113","theaterChainName":"Regal Cinemas","ticketType":"STANDARD"}]