[{"id":"209","tribuneTheaterId":"7773","providerTheaterId":"","name":"Harvard Cinema","address":"3161 W. Harvard Ave","city":"Roseburg","state":"OR","zip":"97471","distance":7.1207759427849,"lon":"-123.388806","lat":"43.214321","theaterChainName":"Independent Chains","ticketType":"STANDARD"},{"id":"1817","tribuneTheaterId":"4997","providerTheaterId":"","name":"Garden Valley Cinema","address":"1750 N.W. Hughwood","city":"Roseburg","state":"OR","zip":"97471","distance":8.7098867664743,"lon":"-123.380295","lat":"43.236508","theaterChainName":"Independent Chains","ticketType":"STANDARD"}]