[{"id":"5061","tribuneTheaterId":"10444","providerTheaterId":"","name":"PFC's Limelight Cinema","address":"1416 Cornwall Ave.","city":"Bellingham","state":"WA","zip":"98225","distance":9.7194163302351,"lon":"-122.477131","lat":"48.751209","theaterChainName":"Independent Chains","ticketType":"STANDARD"},{"id":"2757","tribuneTheaterId":"1213","providerTheaterId":"","name":"Pickford Film Center","address":"1318 Bay St.","city":"Bellingham","state":"WA","zip":"98225","distance":9.5910726177371,"lon":"-122.480223","lat":"48.751582","theaterChainName":"Independent Chains","ticketType":"STANDARD"},{"id":"5237","tribuneTheaterId":"10660","providerTheaterId":"","name":"Barkley Village 16","address":"3005 Cinema Place","city":"Bellingham","state":"WA","zip":"98226","distance":11.326929561478,"lon":"-122.449515","lat":"48.770328","theaterChainName":"Regal Cinemas","ticketType":"STANDARD"},{"id":"4563","tribuneTheaterId":"9705","providerTheaterId":"","name":"Anacortes Cinemas","address":"415 O Avenue","city":"Anacortes","state":"WA","zip":"98221","distance":13.779293984327,"lon":"-122.613602","lat":"48.51861","theaterChainName":"Far Away Entertainment","ticketType":"STANDARD"},{"id":"1593","tribuneTheaterId":"9041","providerTheaterId":"2448","name":"AMC Loews Cascade Mall 14","address":"200 Cascade Mall Dr.","city":"Burlington","state":"WA","zip":"98233","distance":23.275136269305,"lon":"-122.339383","lat":"48.463746","theaterChainName":"AMC Theatres","ticketType":"STANDARD"}]